funminks/__init__.py
funminks/llm_endpoint.py
funminks/mink_llm_based.py
funminks/population.py
funminks-0.1.1.dist-info/licenses/LICENSE
funminks-0.1.1.dist-info/METADATA
funminks-0.1.1.dist-info/WHEEL
funminks-0.1.1.dist-info/top_level.txt
funminks-0.1.1.dist-info/RECORD
